[[{"__type__":"cc.Prefab","_name":"CubeBg","data":{"__id__":1}},{"__type__":"cc.Node","_name":"CubeBg","_children":[{"__id__":2}],"_level":1,"_components":[{"__type__":"cc.Sprite","node":{"__id__":1},"_spriteFrame":{"__uuid__":"9apv6MdEtEn7JvYLo2MwQH"}},{"__type__":"c1d5137ZNhJsZAlX67esxnT","node":{"__id__":1},"cube":{"__id__":3},"yingtao":{"__uuid__":"78mumd3ShOJYgyaCyPPaHK"},"pingguo":{"__uuid__":"cczYmEB/tOTb7CHo3exnqY"},"fanqie":{"__uuid__":"9dK62pqsFHHLuLzaKnxRt2"},"mihoutao":{"__uuid__":"90qEeKHD5JT6RcGBf0JbrD"},"boluo":{"__uuid__":"eanA8YwxtFLrCa8W8dSQn0"},"chengzi":{"__uuid__":"712pxM/jJBO5CVgrIh/xji"}}],"_prefab":{"__type__":"cc.PrefabInfo","root":{"__id__":1},"asset":{"__uuid__":"1arXtHPbZNoKa049mOdCs9"},"fileId":"d5SNxMn2FGMal9WMb6RDdZ"},"_contentSize":{"__type__":"cc.Size","width":124,"height":124},"_position":{"__type__":"cc.Vec3","x":-326.5,"y":455},"_scale":{"__type__":"cc.Vec3","x":1,"y":1,"z":1}},{"__type__":"cc.Node","_name":"Cube","_parent":{"__id__":1},"_level":2,"_components":[{"__id__":3}],"_prefab":{"__type__":"cc.PrefabInfo","root":{"__id__":1},"asset":{"__uuid__":"1arXtHPbZNoKa049mOdCs9"},"fileId":"c50bo/9n9JqquEjqW9tzD5"},"_contentSize":{"__type__":"cc.Size","width":121,"height":125},"_scale":{"__type__":"cc.Vec3","x":1,"y":1,"z":1}},{"__type__":"cc.Sprite","node":{"__id__":2},"_spriteFrame":{"__uuid__":"712pxM/jJBO5CVgrIh/xji"}}],{"__type__":"cc.SpriteFrame","content":{"name":"chengzi","texture":"a58iIo3d1NAJyaQBZbTVdP","rect":[4,2,121,125],"offset":[0.5,-0.5],"originalSize":[128,128],"capInsets":[0,0,0,0]}},{"__type__":"cc.SpriteFrame","content":{"name":"yingtao","texture":"53tMUGBkdNAI9I4afDbLHH","rect":[1,4,126,122],"offset":[0,-1],"originalSize":[128,128],"capInsets":[0,0,0,0]}},{"__type__":"cc.SpriteFrame","content":{"name":"mihoutao","texture":"daSzeJF7VJ3oYWitk7T9+j","rect":[3,1,123,126],"offset":[0.5,0],"originalSize":[128,128],"capInsets":[0,0,0,0]}},{"__type__":"cc.SpriteFrame","content":{"name":"bg_fruit_rec","texture":"43nG3UkJ5CsKaUFycMFD1b","rect":[2,2,124,124],"offset":[0,0],"originalSize":[128,128],"capInsets":[0,0,0,0]}},{"__type__":"cc.SpriteFrame","content":{"name":"fanqie","texture":"05kwRxuE5CULT3By47yaD9","rect":[3,2,121,125],"offset":[-0.5,-0.5],"originalSize":[128,128],"capInsets":[0,0,0,0]}},{"__type__":"cc.SpriteFrame","content":{"name":"pingguo","texture":"29SiDMXjFE65x0lxcb4XCf","rect":[3,3,121,124],"offset":[-0.5,-1],"originalSize":[128,128],"capInsets":[0,0,0,0]}},{"__type__":"cc.SpriteFrame","content":{"name":"boluo","texture":"f91OvThDVPc5YDrg2FC+IL","rect":[1,2,125,124],"offset":[-0.5,0],"originalSize":[128,128],"capInsets":[0,0,0,0]}}]